_pypropagate.so
pypropagate/__init__.py
pypropagate/categorized_dictionary.py
pypropagate/colormaps.py
pypropagate/coordinate_ndarray.py
pypropagate/hankel.py
pypropagate/phase_gradient.py
pypropagate/plot.py
pypropagate/settings.py
pypropagate/solver.py
pypropagate/units.py
pypropagate/presets/__init__.py
pypropagate/presets/boundaries.py
pypropagate/presets/medium.py
pypropagate/presets/settings.py
pypropagate/presets/time.py
pypropagate/progressbar/__init__.py
pypropagate/progressbar/common.py
pypropagate/progressbar/terminal_bar.py
pypropagate/propagators/__init__.py
pypropagate/propagators/cylindrically_symmetric_fresnel.py
pypropagate/propagators/finitedifferences.py
pypropagate/propagators/fresnel.py
pypropagate/propagators/propagator.py
pypropagate/tests/__init__.py
pypropagate/tests/analytical_tests.py
pypropagate-1.2.5.dist-info/METADATA
pypropagate-1.2.5.dist-info/RECORD
pypropagate-1.2.5.dist-info/WHEEL
pypropagate-1.2.5.dist-info/top_level.txt
