Metadata-Version: 2.1
Name: pypropagate
Version: 1.2.5
Summary: A python based paraxial wave propagation framework
Home-page: UNKNOWN
Author: Lars Melchior
Author-email: lars.melchior@gmail.com
License: UNKNOWN
Platform: UNKNOWN
Classifier: Programming Language :: Python :: 2.7
Requires-Dist: matplotlib
Requires-Dist: numpy
Requires-Dist: scipy
Requires-Dist: expresso[pycas]
